{"english":{"ren":8,"whe":10,"lat":26,"ent":23," a":14,"per":14,"hav":18,"ura":9,"ike":9,"eas":8," pa":8,"g  ":86,"o  ":83,"her":19," I":8,"ing":87," bo":8,"sk ":7,"whi":12,"ay ":11,"nce":10,"or ":30,"ry ":37,"tin":18,"ly ":37,"ns ":24,"bra":14,"ial":7,"pen":12," po":9,"ici":7,"con":14,"rom":9,"le ":21,"ir ":8," no":12,"out":9,"und":8,"ess":10," ":58,"ord":16,"eur":23,"sam":7,"as ":9,"n  ":125,"es ":49,"tiv":14,"te ":12,"eco":12,"son":10,"Mus":9,"hap":9,"ifi":8,"mul":20,"hem":11,"emo":31,"rn ":7,"em ":13,"lea":11,"eca":9," Ne":8,"tio":21,"ori":20,"ome":13,"res":11,"abl":10,"imp":8,"e  ":301," n":8,"he ":86," ca":14,"ce ":14,"ot ":9,"er ":20,"als":8,"his":22," o":72,"ed ":26,"eli":12,"all":26,"en ":26," el":13,"th ":13,"ral":11,"ica":12,"the":113,"ey ":8,"hat":45," wh":28,"on ":35,"to ":58,"are":19,"a  ":49,"mor":31,"cor":16,"The":13,"rdi":10," ab":8,"ula":27,"sen":9,"ith":14,"d  ":88," Th":17,"nto":11,"no ":8,"at ":55,"der":7,"ect":15," st":32," Mu":9,"tra":8,"cho":8,"s  ":179,"ani":8,"rod":8," ex":11,"pla":8,"man":8,"se ":28,"ory":21,"cau":8," mo":8,"tha":41,"and":31,"som":11,"h  ":31," co":27,"ati":26,"ll ":29,"l  ":66,"ter":16,"ts ":10,"ve ":30,"ch ":12," do":18,"ele":8,"om ":14,"eir":9,"m  ":29,"you":28,"pik":9,"hei":8,"spi":9,"me ":23,"ble":12," be":21,"lin":9,"f  ":73,"u  ":20,"ave":19,"sti":29,"ou ":20," al":17,"lec":8," th":167,"mea":12,"gin":8," sa":17,"ny ":7,"vit":10," in":23,"k  ":21,"lly":19," pr":18,"for":17,"ty ":16,"ean":12,"wit":12,"cal":11," he":9,"ens":8,"pec":8,"nin":8," me":46,"rin":10,"aus":8,"re ":36," ar":22,"thi":25,"mpl":9,"ons":17,"t  ":176," it":9,"fro":9,"ina":8,"ver":10,"lon":8," ge":9,"one":7,"ur ":11,"tro":8," se":8,"rai":16," fo":17,"ic ":11,"nd ":39," ha":30,"ery":8,"ow ":10,"but":8,"use":17," an":34," sp":19," si":14,"hey":8,"ls ":8,"y  ":135," pe":10,"our":12," yo":28,"ers":10,"ext":10," ma":14,"imu":20,"ron":13,"eve":11,"hin":11,"int":13,"r  ":75,"ain":18,"cti":16,"tic":12,"ivi":11,"pre":11,"   ":156,"it ":36,"pro":11,"ill":19,"ion":22,"act":16,"neu":16,"in ":38,"spe":13,"eri":9,"wil":14,"so ":9," tr":12," br":15,"uro":14,"c  ":11,"rea":15,"ity":11,"w  ":16," so":17,"din":17,"be ":13,"an ":15,"any":9,"nt ":16,"ng ":86,"ear":10,"com":8,"I  ":8," ne":30,"ut ":22,"ead":8,"al ":25,"mem":31,"tim":23,"ich":8,"ant":8,"app":11,"ies":18," us":9," ch":12,"fic":9,"ere":18,"ate":20,"rec":16,"usk":9," fr":10,"rie":15,"ins":7," t":47,"tex":8,"hen":12,"ast":7,"et ":11,"kes":9,"us ":7,"ive":7,"if ":9,"is ":45," i":86,"ple":8,"ge ":8,"rus":7," ac":17,"nal":10,"can":11,"eci":7," b":15," wi":27," di":8,"rs ":8,"ppe":10," re":31," bu":10,"of ":56,"ad ":10}}